{
  "classname": null,
  "name": null,
  "animation": {
    "classname": null,
    "name": "AnimationManager",
    "actionlist": []
  },
  "dataScale": 1,
  "designHeight": 800,
  "designWidth": 1280,
  "textures": [
    "battle0.plist"
  ],
  "texturesPng": [
    "battle0.png"
  ],
  "version": "1.6.0.0",
  "widgetTree": {
    "classname": "Panel",
    "name": null,
    "children": [
      {
        "classname": "ImageView",
        "name": null,
        "children": [
          {
            "classname": "Label",
            "name": null,
            "children": [],
            "options": {
              "__type": "LabelSurrogate:#EditorCommon.JsonModel.Component.GUI",
              "classname": "Label",
              "name": "Label_14",
              "ZOrder": 0,
              "actiontag": 13085393,
              "anchorPointX": 0,
              "anchorPointY": 0,
              "classType": "CocoStudio.EngineAdapterWrap.CSLabel",
              "colorB": 255,
              "colorG": 255,
              "colorR": 255,
              "customProperty": "",
              "flipX": false,
              "flipY": false,
              "height": 27,
              "ignoreSize": true,
              "layoutParameter": null,
              "opacity": 255,
              "positionPercentX": -0.233333334,
              "positionPercentY": -0.3888889,
              "positionType": 0,
              "rotation": 0,
              "scaleX": 1,
              "scaleY": 1,
              "sizePercentX": 0.2857143,
              "sizePercentY": 0.75,
              "sizeType": 0,
              "tag": 17,
              "touchAble": false,
              "useMergedTexture": false,
              "visible": true,
              "width": 60,
              "x": -49,
              "y": -14,
              "areaHeight": 0,
              "areaWidth": 0,
              "fontFile": null,
              "fontName": "微软雅黑",
              "fontSize": 20,
              "hAlignment": 0,
              "text": "血小贱",
              "touchScaleEnable": false,
              "vAlignment": 0
            }
          }
        ],
        "options": {
          "__type": "ImageViewSurrogate:#EditorCommon.JsonModel.Component.GUI",
          "classname": "ImageView",
          "name": "Image_13",
          "ZOrder": 0,
          "actiontag": 54333620,
          "anchorPointX": 0.5,
          "anchorPointY": 0.5,
          "classType": "CocoStudio.EngineAdapterWrap.CSImageView",
          "colorB": 255,
          "colorG": 255,
          "colorR": 255,
          "customProperty": "",
          "flipX": false,
          "flipY": false,
          "height": 36,
          "ignoreSize": true,
          "layoutParameter": null,
          "opacity": 255,
          "positionPercentX": 0.213281244,
          "positionPercentY": 0.90875,
          "positionType": 0,
          "rotation": 0,
          "scaleX": 1,
          "scaleY": 1,
          "sizePercentX": 0.1640625,
          "sizePercentY": 0.045,
          "sizeType": 0,
          "tag": 16,
          "touchAble": false,
          "useMergedTexture": false,
          "visible": true,
          "width": 210,
          "x": 273,
          "y": 727,
          "capInsetsHeight": 1,
          "capInsetsWidth": 1,
          "capInsetsX": 0,
          "capInsetsY": 0,
          "fileName": null,
          "fileNameData": {
            "path": "battleui/012.png",
            "plistFile": "",
            "resourceType": 0
          },
          "scale9Enable": false,
          "scale9Height": 36,
          "scale9Width": 210
        }
      },
      {
        "classname": "ImageView",
        "name": null,
        "children": [
          {
            "classname": "LoadingBar",
            "name": null,
            "children": [],
            "options": {
              "__type": "LoadingBarSurrogate:#EditorCommon.JsonModel.Component.GUI",
              "classname": "LoadingBar",
              "name": "leaderhpbar",
              "ZOrder": 0,
              "actiontag": 10826121,
              "anchorPointX": 0.5,
              "anchorPointY": 0.5,
              "classType": "CocoStudio.EngineAdapterWrap.CSLoadingBar",
              "colorB": 255,
              "colorG": 255,
              "colorR": 255,
              "customProperty": "",
              "flipX": false,
              "flipY": false,
              "height": 17,
              "ignoreSize": true,
              "layoutParameter": null,
              "opacity": 255,
              "positionPercentX": 0.199404761,
              "positionPercentY": -0.04410956,
              "positionType": 0,
              "rotation": 0,
              "scaleX": 1,
              "scaleY": 1,
              "sizePercentX": 1.04166663,
              "sizePercentY": 1.2,
              "sizeType": 0,
              "tag": 38,
              "touchAble": false,
              "useMergedTexture": false,
              "visible": true,
              "width": 199,
              "x": 67,
              "y": 0,
              "capInsetsHeight": 1,
              "capInsetsWidth": 1,
              "capInsetsX": 0,
              "capInsetsY": 0,
              "direction": 0,
              "percent": 73,
              "scale9Enable": false,
              "texture": null,
              "textureData": {
                "path": "battleui/008.png",
                "plistFile": "",
                "resourceType": 0
              }
            }
          }
        ],
        "options": {
          "__type": "ImageViewSurrogate:#EditorCommon.JsonModel.Component.GUI",
          "classname": "ImageView",
          "name": "Image_15",
          "ZOrder": 0,
          "actiontag": 44040229,
          "anchorPointX": 0.5,
          "anchorPointY": 0.5,
          "classType": "CocoStudio.EngineAdapterWrap.CSImageView",
          "colorB": 255,
          "colorG": 255,
          "colorR": 255,
          "customProperty": "",
          "flipX": false,
          "flipY": false,
          "height": 20,
          "ignoreSize": true,
          "layoutParameter": null,
          "opacity": 255,
          "positionPercentX": 0.1703125,
          "positionPercentY": 0.87375,
          "positionType": 0,
          "rotation": 0,
          "scaleX": 1,
          "scaleY": 1,
          "sizePercentX": 0.2625,
          "sizePercentY": 0.025,
          "sizeType": 0,
          "tag": 18,
          "touchAble": false,
          "useMergedTexture": false,
          "visible": true,
          "width": 336,
          "x": 218,
          "y": 699,
          "capInsetsHeight": 1,
          "capInsetsWidth": 1,
          "capInsetsX": 0,
          "capInsetsY": 0,
          "fileName": null,
          "fileNameData": {
            "path": "battleui/015.png",
            "plistFile": "",
            "resourceType": 0
          },
          "scale9Enable": false,
          "scale9Height": 20,
          "scale9Width": 336
        }
      },
      {
        "classname": "ImageView",
        "name": null,
        "children": [
          {
            "classname": "ImageView",
            "name": null,
            "children": [
              {
                "classname": "Label",
                "name": null,
                "children": [],
                "options": {
                  "__type": "LabelSurrogate:#EditorCommon.JsonModel.Component.GUI",
                  "classname": "Label",
                  "name": "Label_12",
                  "ZOrder": 0,
                  "actiontag": 14506838,
                  "anchorPointX": 0.5,
                  "anchorPointY": 0.5,
                  "classType": "CocoStudio.EngineAdapterWrap.CSLabel",
                  "colorB": 255,
                  "colorG": 255,
                  "colorR": 255,
                  "customProperty": "",
                  "flipX": false,
                  "flipY": false,
                  "height": 27,
                  "ignoreSize": true,
                  "layoutParameter": null,
                  "opacity": 255,
                  "positionPercentX": 0,
                  "positionPercentY": 0,
                  "positionType": 0,
                  "rotation": 0,
                  "scaleX": 1,
                  "scaleY": 1,
                  "sizePercentX": 0.558139563,
                  "sizePercentY": 0.627907,
                  "sizeType": 0,
                  "tag": 15,
                  "touchAble": false,
                  "useMergedTexture": false,
                  "visible": true,
                  "width": 24,
                  "x": 0,
                  "y": 0,
                  "areaHeight": 0,
                  "areaWidth": 0,
                  "fontFile": null,
                  "fontName": "微软雅黑",
                  "fontSize": 20,
                  "hAlignment": 1,
                  "text": "17",
                  "touchScaleEnable": false,
                  "vAlignment": 1
                }
              }
            ],
            "options": {
              "__type": "ImageViewSurrogate:#EditorCommon.JsonModel.Component.GUI",
              "classname": "ImageView",
              "name": "Image_11",
              "ZOrder": 0,
              "actiontag": 24835906,
              "anchorPointX": 0.5,
              "anchorPointY": 0.5,
              "classType": "CocoStudio.EngineAdapterWrap.CSImageView",
              "colorB": 255,
              "colorG": 255,
              "colorR": 255,
              "customProperty": "",
              "flipX": false,
              "flipY": false,
              "height": 43,
              "ignoreSize": true,
              "layoutParameter": null,
              "opacity": 255,
              "positionPercentX": 0.389261752,
              "positionPercentY": 0.367346942,
              "positionType": 0,
              "rotation": 0,
              "scaleX": 1,
              "scaleY": 1,
              "sizePercentX": 0.2885906,
              "sizePercentY": 0.292517,
              "sizeType": 0,
              "tag": 14,
              "touchAble": false,
              "useMergedTexture": false,
              "visible": true,
              "width": 43,
              "x": 58,
              "y": 54,
              "capInsetsHeight": 1,
              "capInsetsWidth": 1,
              "capInsetsX": 0,
              "capInsetsY": 0,
              "fileName": null,
              "fileNameData": {
                "path": "battleui/011.png",
                "plistFile": "",
                "resourceType": 0
              },
              "scale9Enable": false,
              "scale9Height": 43,
              "scale9Width": 43
            }
          },
          {
            "classname": "ImageView",
            "name": null,
            "children": [],
            "options": {
              "__type": "ImageViewSurrogate:#EditorCommon.JsonModel.Component.GUI",
              "classname": "ImageView",
              "name": "leadericon",
              "ZOrder": 0,
              "actiontag": 43251701,
              "anchorPointX": 0.5,
              "anchorPointY": 0.5,
              "classType": "CocoStudio.EngineAdapterWrap.CSImageView",
              "colorB": 255,
              "colorG": 255,
              "colorR": 255,
              "customProperty": "",
              "flipX": false,
              "flipY": false,
              "height": 86,
              "ignoreSize": true,
              "layoutParameter": null,
              "opacity": 255,
              "positionPercentX": 0,
              "positionPercentY": 0,
              "positionType": 0,
              "rotation": 0,
              "scaleX": 1,
              "scaleY": 1,
              "sizePercentX": 0.583892643,
              "sizePercentY": 0.585034,
              "sizeType": 0,
              "tag": 23,
              "touchAble": false,
              "useMergedTexture": false,
              "visible": true,
              "width": 87,
              "x": 0,
              "y": 0,
              "capInsetsHeight": 1,
              "capInsetsWidth": 1,
              "capInsetsX": 0,
              "capInsetsY": 0,
              "fileName": null,
              "fileNameData": {
                "path": "battleui/003.png",
                "plistFile": "",
                "resourceType": 0
              },
              "scale9Enable": false,
              "scale9Height": 86,
              "scale9Width": 87
            }
          }
        ],
        "options": {
          "__type": "ImageViewSurrogate:#EditorCommon.JsonModel.Component.GUI",
          "classname": "ImageView",
          "name": "Image_10",
          "ZOrder": 0,
          "actiontag": 55514217,
          "anchorPointX": 0.5,
          "anchorPointY": 0.5,
          "classType": "CocoStudio.EngineAdapterWrap.CSImageView",
          "colorB": 255,
          "colorG": 255,
          "colorR": 255,
          "customProperty": "",
          "flipX": false,
          "flipY": false,
          "height": 147,
          "ignoreSize": true,
          "layoutParameter": null,
          "opacity": 255,
          "positionPercentX": 0.090625,
          "positionPercentY": 0.85375,
          "positionType": 0,
          "rotation": 0,
          "scaleX": 1,
          "scaleY": 1,
          "sizePercentX": 0.116406247,
          "sizePercentY": 0.18375,
          "sizeType": 0,
          "tag": 13,
          "touchAble": false,
          "useMergedTexture": false,
          "visible": true,
          "width": 149,
          "x": 116,
          "y": 683,
          "capInsetsHeight": 1,
          "capInsetsWidth": 1,
          "capInsetsX": 0,
          "capInsetsY": 0,
          "fileName": null,
          "fileNameData": {
            "path": "battleui/017.png",
            "plistFile": "",
            "resourceType": 0
          },
          "scale9Enable": false,
          "scale9Height": 147,
          "scale9Width": 149
        }
      },
      {
        "classname": "Panel",
        "name": null,
        "children": [
          {
            "classname": "ImageView",
            "name": null,
            "children": [
              {
                "classname": "LoadingBar",
                "name": null,
                "children": [],
                "options": {
                  "__type": "LoadingBarSurrogate:#EditorCommon.JsonModel.Component.GUI",
                  "classname": "LoadingBar",
                  "name": "enemyhpbar",
                  "ZOrder": 0,
                  "actiontag": 20897367,
                  "anchorPointX": 0.5,
                  "anchorPointY": 0.5,
                  "classType": "CocoStudio.EngineAdapterWrap.CSLoadingBar",
                  "colorB": 255,
                  "colorG": 255,
                  "colorR": 255,
                  "customProperty": "",
                  "flipX": false,
                  "flipY": false,
                  "height": 17,
                  "ignoreSize": true,
                  "layoutParameter": null,
                  "opacity": 255,
                  "positionPercentX": -0.197990492,
                  "positionPercentY": -0.0607867241,
                  "positionType": 0,
                  "rotation": 0,
                  "scaleX": 1,
                  "scaleY": 1,
                  "sizePercentX": 1.04166663,
                  "sizePercentY": 1.2,
                  "sizeType": 0,
                  "tag": 40,
                  "touchAble": false,
                  "useMergedTexture": false,
                  "visible": true,
                  "width": 199,
                  "x": -66,
                  "y": -1,
                  "capInsetsHeight": 1,
                  "capInsetsWidth": 1,
                  "capInsetsX": 0,
                  "capInsetsY": 0,
                  "direction": 1,
                  "percent": 69,
                  "scale9Enable": false,
                  "texture": null,
                  "textureData": {
                    "path": "battleui/008.png",
                    "plistFile": "",
                    "resourceType": 0
                  }
                }
              }
            ],
            "options": {
              "__type": "ImageViewSurrogate:#EditorCommon.JsonModel.Component.GUI",
              "classname": "ImageView",
              "name": "Image_23",
              "ZOrder": 0,
              "actiontag": 41789875,
              "anchorPointX": 0.5,
              "anchorPointY": 0.5,
              "classType": "CocoStudio.EngineAdapterWrap.CSImageView",
              "colorB": 255,
              "colorG": 255,
              "colorR": 255,
              "customProperty": "",
              "flipX": false,
              "flipY": false,
              "height": 20,
              "ignoreSize": true,
              "layoutParameter": null,
              "opacity": 255,
              "positionPercentX": -10155.0938,
              "positionPercentY": 1572.81628,
              "positionType": 0,
              "rotation": 0,
              "scaleX": 1,
              "scaleY": 1,
              "sizePercentX": 8000,
              "sizePercentY": 8000,
              "sizeType": 0,
              "tag": 39,
              "touchAble": false,
              "useMergedTexture": false,
              "visible": true,
              "width": 336,
              "x": -101,
              "y": 15,
              "capInsetsHeight": 1,
              "capInsetsWidth": 1,
              "capInsetsX": 0,
              "capInsetsY": 0,
              "fileName": null,
              "fileNameData": {
                "path": "battleui/015.png",
                "plistFile": "",
                "resourceType": 0
              },
              "scale9Enable": false,
              "scale9Height": 20,
              "scale9Width": 336
            }
          },
          {
            "classname": "ImageView",
            "name": null,
            "children": [
              {
                "classname": "Label",
                "name": null,
                "children": [],
                "options": {
                  "__type": "LabelSurrogate:#EditorCommon.JsonModel.Component.GUI",
                  "classname": "Label",
                  "name": "Label_25",
                  "ZOrder": 0,
                  "actiontag": 59827474,
                  "anchorPointX": 1,
                  "anchorPointY": 0,
                  "classType": "CocoStudio.EngineAdapterWrap.CSLabel",
                  "colorB": 255,
                  "colorG": 255,
                  "colorR": 255,
                  "customProperty": "",
                  "flipX": false,
                  "flipY": false,
                  "height": 27,
                  "ignoreSize": true,
                  "layoutParameter": null,
                  "opacity": 255,
                  "positionPercentX": -0.233333334,
                  "positionPercentY": -0.3888889,
                  "positionType": 0,
                  "rotation": 0,
                  "scaleX": -1,
                  "scaleY": 1,
                  "sizePercentX": 0.4,
                  "sizePercentY": 0.75,
                  "sizeType": 0,
                  "tag": 33,
                  "touchAble": false,
                  "useMergedTexture": false,
                  "visible": true,
                  "width": 84,
                  "x": -49,
                  "y": -14,
                  "areaHeight": 0,
                  "areaWidth": 0,
                  "fontFile": null,
                  "fontName": "微软雅黑",
                  "fontSize": 20,
                  "hAlignment": 2,
                  "text": "牛头淫11",
                  "touchScaleEnable": false,
                  "vAlignment": 1
                }
              }
            ],
            "options": {
              "__type": "ImageViewSurrogate:#EditorCommon.JsonModel.Component.GUI",
              "classname": "ImageView",
              "name": "Image_22",
              "ZOrder": 0,
              "actiontag": 51772107,
              "anchorPointX": 0.5,
              "anchorPointY": 0.5,
              "classType": "CocoStudio.EngineAdapterWrap.CSImageView",
              "colorB": 255,
              "colorG": 255,
              "colorR": 255,
              "customProperty": "",
              "flipX": false,
              "flipY": false,
              "height": 36,
              "ignoreSize": true,
              "layoutParameter": null,
              "opacity": 255,
              "positionPercentX": -15800,
              "positionPercentY": 4400,
              "positionType": 0,
              "rotation": 0,
              "scaleX": -1,
              "scaleY": 1,
              "sizePercentX": 21000,
              "sizePercentY": 3600,
              "sizeType": 0,
              "tag": 30,
              "touchAble": false,
              "useMergedTexture": false,
              "visible": true,
              "width": 210,
              "x": -158,
              "y": 44,
              "capInsetsHeight": 1,
              "capInsetsWidth": 1,
              "capInsetsX": 0,
              "capInsetsY": 0,
              "fileName": null,
              "fileNameData": {
                "path": "battleui/012.png",
                "plistFile": "",
                "resourceType": 0
              },
              "scale9Enable": false,
              "scale9Height": 36,
              "scale9Width": 210
            }
          },
          {
            "classname": "ImageView",
            "name": null,
            "children": [
              {
                "classname": "ImageView",
                "name": null,
                "children": [
                  {
                    "classname": "Label",
                    "name": null,
                    "children": [],
                    "options": {
                      "__type": "LabelSurrogate:#EditorCommon.JsonModel.Component.GUI",
                      "classname": "Label",
                      "name": "Label_21",
                      "ZOrder": 0,
                      "actiontag": 51250475,
                      "anchorPointX": 0.5,
                      "anchorPointY": 0.5,
                      "classType": "CocoStudio.EngineAdapterWrap.CSLabel",
                      "colorB": 255,
                      "colorG": 255,
                      "colorR": 255,
                      "customProperty": "",
                      "flipX": false,
                      "flipY": false,
                      "height": 27,
                      "ignoreSize": true,
                      "layoutParameter": null,
                      "opacity": 255,
                      "positionPercentX": 0,
                      "positionPercentY": -0.0232558139,
                      "positionType": 0,
                      "rotation": 0,
                      "scaleX": 1,
                      "scaleY": 1,
                      "sizePercentX": 0.558139563,
                      "sizePercentY": 0.627907,
                      "sizeType": 0,
                      "tag": 29,
                      "touchAble": false,
                      "useMergedTexture": false,
                      "visible": true,
                      "width": 24,
                      "x": 0,
                      "y": -1,
                      "areaHeight": 0,
                      "areaWidth": 0,
                      "fontFile": null,
                      "fontName": "微软雅黑",
                      "fontSize": 20,
                      "hAlignment": 0,
                      "text": "50",
                      "touchScaleEnable": false,
                      "vAlignment": 0
                    }
                  }
                ],
                "options": {
                  "__type": "ImageViewSurrogate:#EditorCommon.JsonModel.Component.GUI",
                  "classname": "ImageView",
                  "name": "Image_20",
                  "ZOrder": 0,
                  "actiontag": 36604475,
                  "anchorPointX": 0.5,
                  "anchorPointY": 0.5,
                  "classType": "CocoStudio.EngineAdapterWrap.CSImageView",
                  "colorB": 255,
                  "colorG": 255,
                  "colorR": 255,
                  "customProperty": "",
                  "flipX": false,
                  "flipY": false,
                  "height": 43,
                  "ignoreSize": true,
                  "layoutParameter": null,
                  "opacity": 255,
                  "positionPercentX": -0.389261752,
                  "positionPercentY": 0.367346942,
                  "positionType": 0,
                  "rotation": 0,
                  "scaleX": 1,
                  "scaleY": 1,
                  "sizePercentX": 0.2885906,
                  "sizePercentY": 0.292517,
                  "sizeType": 0,
                  "tag": 28,
                  "touchAble": false,
                  "useMergedTexture": false,
                  "visible": true,
                  "width": 43,
                  "x": -58,
                  "y": 54,
                  "capInsetsHeight": 1,
                  "capInsetsWidth": 1,
                  "capInsetsX": 0,
                  "capInsetsY": 0,
                  "fileName": null,
                  "fileNameData": {
                    "path": "battleui/011.png",
                    "plistFile": "",
                    "resourceType": 0
                  },
                  "scale9Enable": false,
                  "scale9Height": 43,
                  "scale9Width": 43
                }
              },
              {
                "classname": "ImageView",
                "name": null,
                "children": [],
                "options": {
                  "__type": "ImageViewSurrogate:#EditorCommon.JsonModel.Component.GUI",
                  "classname": "ImageView",
                  "name": "enemyicon",
                  "ZOrder": 0,
                  "actiontag": 67061737,
                  "anchorPointX": 0.5,
                  "anchorPointY": 0.5,
                  "classType": "CocoStudio.EngineAdapterWrap.CSImageView",
                  "colorB": 255,
                  "colorG": 255,
                  "colorR": 255,
                  "customProperty": "",
                  "flipX": false,
                  "flipY": false,
                  "height": 86,
                  "ignoreSize": true,
                  "layoutParameter": null,
                  "opacity": 255,
                  "positionPercentX": 0,
                  "positionPercentY": 0,
                  "positionType": 0,
                  "rotation": 0,
                  "scaleX": 1,
                  "scaleY": 1,
                  "sizePercentX": 0.583892643,
                  "sizePercentY": 0.585034,
                  "sizeType": 0,
                  "tag": 34,
                  "touchAble": false,
                  "useMergedTexture": false,
                  "visible": true,
                  "width": 87,
                  "x": 0,
                  "y": 0,
                  "capInsetsHeight": 1,
                  "capInsetsWidth": 1,
                  "capInsetsX": 0,
                  "capInsetsY": 0,
                  "fileName": null,
                  "fileNameData": {
                    "path": "battleui/006.png",
                    "plistFile": "",
                    "resourceType": 0
                  },
                  "scale9Enable": false,
                  "scale9Height": 86,
                  "scale9Width": 87
                }
              }
            ],
            "options": {
              "__type": "ImageViewSurrogate:#EditorCommon.JsonModel.Component.GUI",
              "classname": "ImageView",
              "name": "Image_19",
              "ZOrder": 0,
              "actiontag": 30324590,
              "anchorPointX": 0.5,
              "anchorPointY": 0.5,
              "classType": "CocoStudio.EngineAdapterWrap.CSImageView",
              "colorB": 255,
              "colorG": 255,
              "colorR": 255,
              "customProperty": "",
              "flipX": false,
              "flipY": false,
              "height": 147,
              "ignoreSize": true,
              "layoutParameter": null,
              "opacity": 255,
              "positionPercentX": 0,
              "positionPercentY": 0,
              "positionType": 0,
              "rotation": 0,
              "scaleX": 1,
              "scaleY": 1,
              "sizePercentX": 14900,
              "sizePercentY": 14700,
              "sizeType": 0,
              "tag": 27,
              "touchAble": false,
              "useMergedTexture": false,
              "visible": true,
              "width": 149,
              "x": 0,
              "y": 0,
              "capInsetsHeight": 1,
              "capInsetsWidth": 1,
              "capInsetsX": 0,
              "capInsetsY": 0,
              "fileName": null,
              "fileNameData": {
                "path": "battleui/017.png",
                "plistFile": "",
                "resourceType": 0
              },
              "scale9Enable": false,
              "scale9Height": 147,
              "scale9Width": 149
            }
          }
        ],
        "options": {
          "__type": "PanelSurrogate:#EditorCommon.JsonModel.Component.GUI",
          "classname": "Panel",
          "name": "enemypanel",
          "ZOrder": 0,
          "actiontag": 49511398,
          "anchorPointX": 1,
          "anchorPointY": 1,
          "classType": "CocoStudio.EngineAdapterWrap.CSPanel",
          "colorB": 255,
          "colorG": 255,
          "colorR": 255,
          "customProperty": "",
          "flipX": false,
          "flipY": false,
          "height": 0.01,
          "ignoreSize": false,
          "layoutParameter": null,
          "opacity": 255,
          "positionPercentX": 0.909375,
          "positionPercentY": 0.85375,
          "positionType": 0,
          "rotation": 0,
          "scaleX": 1,
          "scaleY": 1,
          "sizePercentX": 7.81249946E-06,
          "sizePercentY": 1.25E-05,
          "sizeType": 0,
          "tag": 26,
          "touchAble": true,
          "useMergedTexture": false,
          "visible": true,
          "width": 0.01,
          "x": 1164,
          "y": 683,
          "adaptScreen": false,
          "backGroundImage": null,
          "backGroundImageData": null,
          "backGroundScale9Enable": false,
          "bgColorB": 255,
          "bgColorG": 200,
          "bgColorOpacity": 0,
          "bgColorR": 150,
          "bgEndColorB": 255,
          "bgEndColorG": 200,
          "bgEndColorR": 150,
          "bgStartColorB": 255,
          "bgStartColorG": 255,
          "bgStartColorR": 255,
          "capInsetsHeight": 1,
          "capInsetsWidth": 1,
          "capInsetsX": 0,
          "capInsetsY": 0,
          "clipAble": false,
          "colorType": 1,
          "layoutType": 0,
          "vectorX": 0,
          "vectorY": -0.5
        }
      },
      {
        "classname": "Button",
        "name": null,
        "children": [
          {
            "classname": "ImageView",
            "name": null,
            "children": [],
            "options": {
              "__type": "ImageViewSurrogate:#EditorCommon.JsonModel.Component.GUI",
              "classname": "ImageView",
              "name": "Image_26",
              "ZOrder": 0,
              "actiontag": 56297569,
              "anchorPointX": 0.5,
              "anchorPointY": 0.5,
              "classType": "CocoStudio.EngineAdapterWrap.CSImageView",
              "colorB": 255,
              "colorG": 255,
              "colorR": 255,
              "customProperty": "",
              "flipX": false,
              "flipY": false,
              "height": 102,
              "ignoreSize": true,
              "layoutParameter": null,
              "opacity": 255,
              "positionPercentX": 0,
              "positionPercentY": 0,
              "positionType": 0,
              "rotation": 0,
              "scaleX": 1,
              "scaleY": 1,
              "sizePercentX": 0.536912739,
              "sizePercentY": 0.5442177,
              "sizeType": 0,
              "tag": 42,
              "touchAble": false,
              "useMergedTexture": false,
              "visible": true,
              "width": 102,
              "x": 0,
              "y": 0,
              "capInsetsHeight": 1,
              "capInsetsWidth": 1,
              "capInsetsX": 0,
              "capInsetsY": 0,
              "fileName": null,
              "fileNameData": {
                "path": "battleui/019.png",
                "plistFile": "",
                "resourceType": 0
              },
              "scale9Enable": false,
              "scale9Height": 102,
              "scale9Width": 102
            }
          }
        ],
        "options": {
          "__type": "ButtonSurrogate:#EditorCommon.JsonModel.Component.GUI",
          "classname": "Button",
          "name": "changetargetbtn",
          "ZOrder": 0,
          "actiontag": 8389130,
          "anchorPointX": 0.5,
          "anchorPointY": 0.5,
          "classType": "CocoStudio.EngineAdapterWrap.CSButton",
          "colorB": 255,
          "colorG": 255,
          "colorR": 255,
          "customProperty": "",
          "flipX": false,
          "flipY": false,
          "height": 147,
          "ignoreSize": true,
          "layoutParameter": null,
          "opacity": 255,
          "positionPercentX": 0.9085938,
          "positionPercentY": 0.14,
          "positionType": 0,
          "rotation": 0,
          "scaleX": 1,
          "scaleY": 1,
          "sizePercentX": 0.08046875,
          "sizePercentY": 0.05,
          "sizeType": 0,
          "tag": 41,
          "touchAble": true,
          "useMergedTexture": false,
          "visible": true,
          "width": 149,
          "x": 1163,
          "y": 112,
          "capInsetsHeight": 1,
          "capInsetsWidth": 1,
          "capInsetsX": 0,
          "capInsetsY": 0,
          "disabled": null,
          "disabledData": {
            "path": null,
            "plistFile": null,
            "resourceType": 0
          },
          "fontName": "微软雅黑",
          "fontSize": 14,
          "fontType": 0,
          "normal": null,
          "normalData": {
            "path": "battleui/017.png",
            "plistFile": "",
            "resourceType": 0
          },
          "pressed": null,
          "pressedData": {
            "path": null,
            "plistFile": null,
            "resourceType": 0
          },
          "scale9Enable": false,
          "scale9Height": 147,
          "scale9Width": 149,
          "text": "",
          "textColorB": 255,
          "textColorG": 255,
          "textColorR": 255
        }
      },
      {
        "classname": "Button",
        "name": null,
        "children": [
          {
            "classname": "ImageView",
            "name": null,
            "children": [],
            "options": {
              "__type": "ImageViewSurrogate:#EditorCommon.JsonModel.Component.GUI",
              "classname": "ImageView",
              "name": "Image_28",
              "ZOrder": 0,
              "actiontag": 35390778,
              "anchorPointX": 0.5,
              "anchorPointY": 0.5,
              "classType": "CocoStudio.EngineAdapterWrap.CSImageView",
              "colorB": 255,
              "colorG": 255,
              "colorR": 255,
              "customProperty": "",
              "flipX": false,
              "flipY": false,
              "height": 77,
              "ignoreSize": true,
              "layoutParameter": null,
              "opacity": 255,
              "positionPercentX": 0,
              "positionPercentY": 0,
              "positionType": 0,
              "rotation": 0,
              "scaleX": 1,
              "scaleY": 1,
              "sizePercentX": 0.7207207,
              "sizePercentY": 0.733944952,
              "sizeType": 0,
              "tag": 44,
              "touchAble": false,
              "useMergedTexture": false,
              "visible": true,
              "width": 76,
              "x": 0,
              "y": 0,
              "capInsetsHeight": 1,
              "capInsetsWidth": 1,
              "capInsetsX": 0,
              "capInsetsY": 0,
              "fileName": null,
              "fileNameData": {
                "path": "battleui/020.png",
                "plistFile": "",
                "resourceType": 0
              },
              "scale9Enable": false,
              "scale9Height": 77,
              "scale9Width": 76
            }
          }
        ],
        "options": {
          "__type": "ButtonSurrogate:#EditorCommon.JsonModel.Component.GUI",
          "classname": "Button",
          "name": "jihuobtn",
          "ZOrder": 0,
          "actiontag": 47716441,
          "anchorPointX": 0.5,
          "anchorPointY": 0.5,
          "classType": "CocoStudio.EngineAdapterWrap.CSButton",
          "colorB": 255,
          "colorG": 255,
          "colorR": 255,
          "customProperty": "",
          "flipX": false,
          "flipY": false,
          "height": 109,
          "ignoreSize": true,
          "layoutParameter": null,
          "opacity": 255,
          "positionPercentX": 0.774218738,
          "positionPercentY": 0.14,
          "positionType": 0,
          "rotation": 0,
          "scaleX": 1,
          "scaleY": 1,
          "sizePercentX": 0.08046875,
          "sizePercentY": 0.05,
          "sizeType": 0,
          "tag": 43,
          "touchAble": true,
          "useMergedTexture": false,
          "visible": true,
          "width": 111,
          "x": 991,
          "y": 112,
          "capInsetsHeight": 1,
          "capInsetsWidth": 1,
          "capInsetsX": 0,
          "capInsetsY": 0,
          "disabled": null,
          "disabledData": {
            "path": null,
            "plistFile": null,
            "resourceType": 0
          },
          "fontName": "微软雅黑",
          "fontSize": 14,
          "fontType": 0,
          "normal": null,
          "normalData": {
            "path": "battleui/018.png",
            "plistFile": "",
            "resourceType": 0
          },
          "pressed": null,
          "pressedData": {
            "path": null,
            "plistFile": null,
            "resourceType": 0
          },
          "scale9Enable": false,
          "scale9Height": 109,
          "scale9Width": 111,
          "text": "",
          "textColorB": 255,
          "textColorG": 255,
          "textColorR": 255
        }
      },
      {
        "classname": "Button",
        "name": null,
        "children": [
          {
            "classname": "ImageView",
            "name": null,
            "children": [],
            "options": {
              "__type": "ImageViewSurrogate:#EditorCommon.JsonModel.Component.GUI",
              "classname": "ImageView",
              "name": "Image_30",
              "ZOrder": 0,
              "actiontag": 32522224,
              "anchorPointX": 0.5,
              "anchorPointY": 0.5,
              "classType": "CocoStudio.EngineAdapterWrap.CSImageView",
              "colorB": 255,
              "colorG": 255,
              "colorR": 255,
              "customProperty": "",
              "flipX": false,
              "flipY": false,
              "height": 77,
              "ignoreSize": true,
              "layoutParameter": null,
              "opacity": 255,
              "positionPercentX": -4.52136135E-07,
              "positionPercentY": 0,
              "positionType": 0,
              "rotation": 0,
              "scaleX": 1,
              "scaleY": 1,
              "sizePercentX": 0.7207207,
              "sizePercentY": 0.733944952,
              "sizeType": 0,
              "tag": 46,
              "touchAble": false,
              "useMergedTexture": false,
              "visible": true,
              "width": 76,
              "x": 0,
              "y": 0,
              "capInsetsHeight": 1,
              "capInsetsWidth": 1,
              "capInsetsX": 0,
              "capInsetsY": 0,
              "fileName": null,
              "fileNameData": {
                "path": "battleui/021.png",
                "plistFile": "",
                "resourceType": 0
              },
              "scale9Enable": false,
              "scale9Height": 77,
              "scale9Width": 76
            }
          }
        ],
        "options": {
          "__type": "ButtonSurrogate:#EditorCommon.JsonModel.Component.GUI",
          "classname": "Button",
          "name": "skillbtn",
          "ZOrder": 0,
          "actiontag": 21363070,
          "anchorPointX": 0.5,
          "anchorPointY": 0.5,
          "classType": "CocoStudio.EngineAdapterWrap.CSButton",
          "colorB": 255,
          "colorG": 255,
          "colorR": 255,
          "customProperty": "",
          "flipX": false,
          "flipY": false,
          "height": 109,
          "ignoreSize": true,
          "layoutParameter": null,
          "opacity": 255,
          "positionPercentX": 0.9085938,
          "positionPercentY": 0.3425,
          "positionType": 0,
          "rotation": 0,
          "scaleX": 1,
          "scaleY": 1,
          "sizePercentX": 0.08046875,
          "sizePercentY": 0.05,
          "sizeType": 0,
          "tag": 45,
          "touchAble": true,
          "useMergedTexture": false,
          "visible": true,
          "width": 111,
          "x": 1163,
          "y": 274,
          "capInsetsHeight": 1,
          "capInsetsWidth": 1,
          "capInsetsX": 0,
          "capInsetsY": 0,
          "disabled": null,
          "disabledData": {
            "path": null,
            "plistFile": null,
            "resourceType": 0
          },
          "fontName": "微软雅黑",
          "fontSize": 14,
          "fontType": 0,
          "normal": null,
          "normalData": {
            "path": "battleui/018.png",
            "plistFile": "",
            "resourceType": 0
          },
          "pressed": null,
          "pressedData": {
            "path": null,
            "plistFile": null,
            "resourceType": 0
          },
          "scale9Enable": false,
          "scale9Height": 109,
          "scale9Width": 111,
          "text": "",
          "textColorB": 255,
          "textColorG": 255,
          "textColorR": 255
        }
      }
    ],
    "options": {
      "__type": "PanelSurrogate:#EditorCommon.JsonModel.Component.GUI",
      "classname": "Panel",
      "name": "Panel_1",
      "ZOrder": 0,
      "actiontag": -1,
      "anchorPointX": 0,
      "anchorPointY": 0,
      "classType": "CocoStudio.EngineAdapterWrap.CSPanel",
      "colorB": 255,
      "colorG": 255,
      "colorR": 255,
      "customProperty": "",
      "flipX": false,
      "flipY": false,
      "height": 800,
      "ignoreSize": false,
      "layoutParameter": null,
      "opacity": 255,
      "positionPercentX": 0,
      "positionPercentY": 0,
      "positionType": 0,
      "rotation": 0,
      "scaleX": 1,
      "scaleY": 1,
      "sizePercentX": 1,
      "sizePercentY": 1,
      "sizeType": 0,
      "tag": 1,
      "touchAble": true,
      "useMergedTexture": false,
      "visible": true,
      "width": 1280,
      "x": 0,
      "y": 0,
      "adaptScreen": false,
      "backGroundImage": null,
      "backGroundImageData": null,
      "backGroundScale9Enable": false,
      "bgColorB": 255,
      "bgColorG": 200,
      "bgColorOpacity": 0,
      "bgColorR": 150,
      "bgEndColorB": 255,
      "bgEndColorG": 200,
      "bgEndColorR": 150,
      "bgStartColorB": 255,
      "bgStartColorG": 255,
      "bgStartColorR": 255,
      "capInsetsHeight": 1,
      "capInsetsWidth": 1,
      "capInsetsX": 0,
      "capInsetsY": 0,
      "clipAble": false,
      "colorType": 1,
      "layoutType": 0,
      "vectorX": 0,
      "vectorY": -0.5
    }
  }
}